rankmetrics/__init__.py
rankmetrics/metrics.py
rankmetrics/version.py
rankmetrics-1.0.0.dist-info/DESCRIPTION.rst
rankmetrics-1.0.0.dist-info/METADATA
rankmetrics-1.0.0.dist-info/RECORD
rankmetrics-1.0.0.dist-info/WHEEL
rankmetrics-1.0.0.dist-info/metadata.json
rankmetrics-1.0.0.dist-info/top_level.txt
