Metadata-Version: 2.0
Name: rankmetrics
Version: 1.0.0
Summary: Calculate various metrics relevant for learning to rank algorithms.
Home-page: https://github.com/sorenlind/rankmetrics/
Author: Soren Lind Kristiansen
Author-email: soren@gutsandglory.dk
License: UNKNOWN
Keywords: recommender system learning to rank python
Platform: UNKNOWN
Classifier: Development Status :: 3 - Alpha
Classifier: Intended Audience :: Developers
Classifier: Intended Audience :: Science/Research
Classifier: License :: OSI Approved :: MIT License
Classifier: Operating System :: OS Independent
Classifier: Programming Language :: Python :: 3.6
Requires-Dist: numpy
Requires-Dist: scipy
Requires-Dist: sklearn
Provides-Extra: test
Requires-Dist: pytest; extra == 'test'
Requires-Dist: tox; extra == 'test'
Requires-Dist: pandas; extra == 'test'
